[
  {
    "description": "",
    "elements": [
      {
        "description": "",
        "id": "orders;user-placing-slsu-order",
        "keyword": "Scenario",
        "line": 3,
        "name": "User placing SLSU order",
        "steps": [
          {
            "keyword": "Before",
            "hidden": true,
            "result": {
              "status": "passed",
              "duration": 866420700
            }
          },
          {
            "arguments": [],
            "keyword": "When ",
            "line": 4,
            "name": "user launch the application",
            "match": {
              "location": "Feature\\steps\\Homepage\\Homepage.ts:4"
            },
            "result": {
              "status": "passed",
              "duration": 11168479200
            }
          },
          {
            "arguments": [],
            "keyword": "Given ",
            "line": 5,
            "name": "user naviagate to PLP page",
            "match": {
              "location": "Feature\\steps\\Homepage\\Homepage.ts:10"
            },
            "result": {
              "status": "passed",
              "duration": 5849416699
            }
          },
          {
            "arguments": [],
            "keyword": "Then ",
            "line": 6,
            "name": "user navigate to PDP page",
            "match": {
              "location": "Feature\\steps\\PLPpage\\Plp.ts:5"
            },
            "result": {
              "status": "passed",
              "duration": 3885634500
            }
          },
          {
            "arguments": [],
            "keyword": "Then ",
            "line": 7,
            "name": "user add product to cart",
            "match": {
              "location": "Feature\\steps\\PDPpge\\Pdp.ts:4"
            },
            "result": {
              "status": "passed",
              "duration": 9775986099
            }
          },
          {
            "arguments": [],
            "keyword": "Then ",
            "line": 8,
            "name": "user navigate to cart page",
            "match": {
              "location": "Feature\\steps\\PDPpge\\Pdp.ts:8"
            },
            "result": {
              "status": "passed",
              "duration": 2604035900
            }
          },
          {
            "arguments": [],
            "keyword": "Then ",
            "line": 9,
            "name": "user proceed to checkout",
            "match": {
              "location": "Feature\\steps\\Cart\\Cart.ts:3"
            },
            "result": {
              "status": "passed",
              "duration": 165800
            }
          },
          {
            "arguments": [],
            "keyword": "Then ",
            "line": 10,
            "name": "user enter shipping details",
            "match": {
              "location": "Feature\\steps\\Checkout\\Checkout.ts:3"
            },
            "result": {
              "status": "passed",
              "duration": 142599
            }
          },
          {
            "arguments": [],
            "keyword": "Then ",
            "line": 11,
            "name": "user enter payment details",
            "match": {
              "location": "Feature\\steps\\Checkout\\Checkout.ts:7"
            },
            "result": {
              "status": "passed",
              "duration": 230900
            }
          },
          {
            "arguments": [],
            "keyword": "Then ",
            "line": 12,
            "name": "user place the order",
            "match": {
              "location": "Feature\\steps\\Checkout\\Checkout.ts:10"
            },
            "result": {
              "status": "passed",
              "duration": 582300
            }
          },
          {
            "arguments": [],
            "keyword": "Then ",
            "line": 13,
            "name": "user verify order confirmation page",
            "match": {
              "location": "Feature\\steps\\orderconfirmation\\orderconfirmation.ts:5"
            },
            "result": {
              "status": "passed",
              "duration": 173199
            }
          },
          {
            "keyword": "After",
            "hidden": true,
            "result": {
              "status": "passed",
              "duration": 322899
            }
          },
          {
            "keyword": "After",
            "hidden": true,
            "result": {
              "status": "passed",
              "duration": 166299
            }
          }
        ],
        "tags": [],
        "type": "scenario"
      }
    ],
    "id": "orders",
    "line": 1,
    "keyword": "Feature",
    "name": "Orders",
    "tags": [],
    "uri": "Feature\\Features\\login.feature"
  }
]